{
"type": "FeatureCollection",
"crs": { "type": "name", "properties": { "name": "urn:ogc:def:crs:OGC:1.3:CRS84" } },
                                                                                
"features": [
{ "type": "Feature", "properties": { }, "geometry": { "type": "Point", "coordinates": [ 1398659.130806647939608, 1151020.493670529918745 ] } },
{ "type": "Feature", "properties": { }, "geometry": { "type": "Point", "coordinates": [ 1398458.46622935985215, 1151020.773990825051442 ] } },
{ "type": "Feature", "properties": { }, "geometry": { "type": "Point", "coordinates": [ 1402104.203299737768248, 1151063.1284267117735 ] } },
{ "type": "Feature", "properties": { }, "geometry": { "type": "Point", "coordinates": [ 1401891.39638883410953, 1151068.561443445505574 ] } },
{ "type": "Feature", "properties": { }, "geometry": { "type": "Point", "coordinates": [ 1401788.336464119842276, 1151067.34542865655385 ] } },
{ "type": "Feature", "properties": { }, "geometry": { "type": "Point", "coordinates": [ 1397040.822968234773725, 1151013.315009211422876 ] } },
{ "type": "Feature", "properties": { }, "geometry": { "type": "Point", "coordinates": [ 1401509.028658048948273, 1151067.359824938932434 ] } },
{ "type": "Feature", "properties": { }, "geometry": { "type": "Point", "coordinates": [ 1401102.914490758208558, 1151064.554028479848057 ] } },
{ "type": "Feature", "properties": { }, "geometry": { "type": "Point", "coordinates": [ 1400668.323239007266238, 1151061.412227934459224 ] } },
{ "type": "Feature", "properties": { }, "geometry": { "type": "Point", "coordinates": [ 1400321.205084493383765, 1151059.964527213945985 ] } },
{ "type": "Feature", "properties": { }, "geometry": { "type": "Point", "coordinates": [ 1399991.037575491704047, 1151058.716828925535083 ] } },
{ "type": "Feature", "properties": { }, "geometry": { "type": "Point", "coordinates": [ 1399401.186177242547274, 1151054.405093372799456 ] } },
{ "type": "Feature", "properties": { }, "geometry": { "type": "Point", "coordinates": [ 1399165.233191712293774, 1151051.621059513883665 ] } },
{ "type": "Feature", "properties": { }, "geometry": { "type": "Point", "coordinates": [ 1398923.224572162609547, 1151052.737548421602696 ] } },
{ "type": "Feature", "properties": { }, "geometry": { "type": "Point", "coordinates": [ 1398220.158394679892808, 1151048.413971167989075 ] } },
{ "type": "Feature", "properties": { }, "geometry": { "type": "Point", "coordinates": [ 1398690.677248522872105, 1151051.317689596442506 ] } },
{ "type": "Feature", "properties": { }, "geometry": { "type": "Point", "coordinates": [ 1397986.933045219862834, 1151046.986112245824188 ] } },
{ "type": "Feature", "properties": { }, "geometry": { "type": "Point", "coordinates": [ 1397612.701624280540273, 1151045.880494906799868 ] } },
{ "type": "Feature", "properties": { }, "geometry": { "type": "Point", "coordinates": [ 1397544.221016411203891, 1151045.072485079988837 ] } },
{ "type": "Feature", "properties": { }, "geometry": { "type": "Point", "coordinates": [ 1397301.487772675929591, 1151042.208450247999281 ] } },
{ "type": "Feature", "properties": { }, "geometry": { "type": "Point", "coordinates": [ 1402102.166872749570757, 1151120.698019136209041 ] } },
{ "type": "Feature", "properties": { }, "geometry": { "type": "Point", "coordinates": [ 1398938.589241549372673, 1151148.90820515435189 ] } },
{ "type": "Feature", "properties": { }, "geometry": { "type": "Point", "coordinates": [ 1398232.591152221430093, 1151183.607776564080268 ] } },
{ "type": "Feature", "properties": { }, "geometry": { "type": "Point", "coordinates": [ 1401511.7678456697613, 1151358.670225279172882 ] } },
{ "type": "Feature", "properties": { }, "geometry": { "type": "Point", "coordinates": [ 1399707.810611617052928, 1151418.148613671539351 ] } },
{ "type": "Feature", "properties": { }, "geometry": { "type": "Point", "coordinates": [ 1399167.501696628984064, 1151418.393408863805234 ] } },
{ "type": "Feature", "properties": { }, "geometry": { "type": "Point", "coordinates": [ 1399407.639332994818687, 1151431.156752412440255 ] } },
{ "type": "Feature", "properties": { }, "geometry": { "type": "Point", "coordinates": [ 1401795.069210062734783, 1151467.932229549624026 ] } },
{ "type": "Feature", "properties": { }, "geometry": { "type": "Point", "coordinates": [ 1401509.628106030868366, 1151465.226275861961767 ] } },
{ "type": "Feature", "properties": { }, "geometry": { "type": "Point", "coordinates": [ 1402106.937788305338472, 1151469.626012484775856 ] } },
{ "type": "Feature", "properties": { }, "geometry": { "type": "Point", "coordinates": [ 1400293.982174652628601, 1151455.516712326323614 ] } },
{ "type": "Feature", "properties": { }, "geometry": { "type": "Point", "coordinates": [ 1401212.005836413009092, 1151464.362582243978977 ] } },
{ "type": "Feature", "properties": { }, "geometry": { "type": "Point", "coordinates": [ 1400910.299879083409905, 1151462.126713494770229 ] } },
{ "type": "Feature", "properties": { }, "geometry": { "type": "Point", "coordinates": [ 1400610.620232821209356, 1151459.252757763490081 ] } },
{ "type": "Feature", "properties": { }, "geometry": { "type": "Point", "coordinates": [ 1400325.849388215690851, 1151455.892716899281368 ] } },
{ "type": "Feature", "properties": { }, "geometry": { "type": "Point", "coordinates": [ 1400024.821456706617028, 1151453.664848247310147 ] } },
{ "type": "Feature", "properties": { }, "geometry": { "type": "Point", "coordinates": [ 1400515.166153621627018, 1151470.70440224558115 ] } },
{ "type": "Feature", "properties": { }, "geometry": { "type": "Point", "coordinates": [ 1402098.410809223772958, 1151494.019240347668529 ] } },
{ "type": "Feature", "properties": { }, "geometry": { "type": "Point", "coordinates": [ 1402099.43832278274931, 1151523.821167762391269 ] } },
{ "type": "Feature", "properties": { }, "geometry": { "type": "Point", "coordinates": [ 1402054.088256751652807, 1151529.906033980892971 ] } },
{ "type": "Feature", "properties": { }, "geometry": { "type": "Point", "coordinates": [ 1401794.404367504175752, 1151526.841996716568246 ] } },
{ "type": "Feature", "properties": { }, "geometry": { "type": "Point", "coordinates": [ 1398696.457795322639868, 1151486.317028528777882 ] } },
{ "type": "Feature", "properties": { }, "geometry": { "type": "Point", "coordinates": [ 1399712.857332207262516, 1151501.619610744295642 ] } },
{ "type": "Feature", "properties": { }, "geometry": { "type": "Point", "coordinates": [ 1399406.389661346096545, 1151498.003566766390577 ] } },
{ "type": "Feature", "properties": { }, "geometry": { "type": "Point", "coordinates": [ 1401386.980746937682852, 1151527.992723705014214 ] } },
{ "type": "Feature", "properties": { }, "geometry": { "type": "Point", "coordinates": [ 1401559.970527892932296, 1151537.977795800194144 ] } },
{ "type": "Feature", "properties": { }, "geometry": { "type": "Point", "coordinates": [ 1401321.28990629222244, 1151533.83758700452745 ] } },
{ "type": "Feature", "properties": { }, "geometry": { "type": "Point", "coordinates": [ 1400875.873540595639497, 1151532.554046723525971 ] } },
{ "type": "Feature", "properties": { }, "geometry": { "type": "Point", "coordinates": [ 1400686.73540225578472, 1151532.970368672860786 ] } },
{ "type": "Feature", "properties": { }, "geometry": { "type": "Point", "coordinates": [ 1400487.411343820160255, 1151531.942514615133405 ] } },
{ "type": "Feature", "properties": { }, "geometry": { "type": "Point", "coordinates": [ 1400404.014167899964377, 1151530.958502647699788 ] } },
{ "type": "Feature", "properties": { }, "geometry": { "type": "Point", "coordinates": [ 1400317.211330089019611, 1151528.610315646510571 ] } },
{ "type": "Feature", "properties": { }, "geometry": { "type": "Point", "coordinates": [ 1400258.269682071404532, 1151531.886830823961645 ] } },
{ "type": "Feature", "properties": { }, "geometry": { "type": "Point", "coordinates": [ 1399511.232789381640032, 1151535.650381804676726 ] } },
{ "type": "Feature", "properties": { }, "geometry": { "type": "Point", "coordinates": [ 1399949.299600571393967, 1151546.115142847644165 ] } },
{ "type": "Feature", "properties": { }, "geometry": { "type": "Point", "coordinates": [ 1399173.053232840960845, 1151544.900078728562221 ] } },
{ "type": "Feature", "properties": { }, "geometry": { "type": "Point", "coordinates": [ 1398698.520588834537193, 1151546.582970632240176 ] } },
{ "type": "Feature", "properties": { }, "geometry": { "type": "Point", "coordinates": [ 1398236.347737480420619, 1151561.651609761640429 ] } },
{ "type": "Feature", "properties": { }, "geometry": { "type": "Point", "coordinates": [ 1398943.629631375195459, 1151578.602845799643546 ] } },
{ "type": "Feature", "properties": { }, "geometry": { "type": "Point", "coordinates": [ 1401407.09159706835635, 1151624.219381118891761 ] } },
{ "type": "Feature", "properties": { }, "geometry": { "type": "Point", "coordinates": [ 1401648.461022768402472, 1151626.405328482855111 ] } },
{ "type": "Feature", "properties": { }, "geometry": { "type": "Point", "coordinates": [ 1401558.977147252066061, 1151626.67349018692039 ] } },
{ "type": "Feature", "properties": { }, "geometry": { "type": "Point", "coordinates": [ 1400894.566207931609824, 1151623.468005752889439 ] } },
{ "type": "Feature", "properties": { }, "geometry": { "type": "Point", "coordinates": [ 1400697.276226957561448, 1151622.464151987340301 ] } },
{ "type": "Feature", "properties": { }, "geometry": { "type": "Point", "coordinates": [ 1401859.428016064921394, 1151637.500493300147355 ] } },
{ "type": "Feature", "properties": { }, "geometry": { "type": "Point", "coordinates": [ 1400464.74443610641174, 1151622.368467709748074 ] } },
{ "type": "Feature", "properties": { }, "geometry": { "type": "Point", "coordinates": [ 1396706.416247556451708, 1151575.375579303363338 ] } },
{ "type": "Feature", "properties": { }, "geometry": { "type": "Point", "coordinates": [ 1402100.134948732797056, 1151641.00261511397548 ] } },
{ "type": "Feature", "properties": { }, "geometry": { "type": "Point", "coordinates": [ 1402058.79867286561057, 1151642.50087099988014 ] } },
{ "type": "Feature", "properties": { }, "geometry": { "type": "Point", "coordinates": [ 1400267.516586285782978, 1151626.661312133772299 ] } },
{ "type": "Feature", "properties": { }, "geometry": { "type": "Point", "coordinates": [ 1399004.362249108031392, 1151612.419218145310879 ] } },
{ "type": "Feature", "properties": { }, "geometry": { "type": "Point", "coordinates": [ 1398699.990786861861125, 1151614.123872648924589 ] } },
{ "type": "Feature", "properties": { }, "geometry": { "type": "Point", "coordinates": [ 1400891.517800173256546, 1151652.559845310170203 ] } },
{ "type": "Feature", "properties": { }, "geometry": { "type": "Point", "coordinates": [ 1400374.877657748525962, 1151647.787945718271658 ] } },
{ "type": "Feature", "properties": { }, "geometry": { "type": "Point", "coordinates": [ 1400318.593748253770173, 1151646.461850368883461 ] } },
{ "type": "Feature", "properties": { }, "geometry": { "type": "Point", "coordinates": [ 1400696.261896660551429, 1151651.579991836566478 ] } },
{ "type": "Feature", "properties": { }, "geometry": { "type": "Point", "coordinates": [ 1400435.915514380903915, 1151649.832129022339359 ] } },
{ "type": "Feature", "properties": { }, "geometry": { "type": "Point", "coordinates": [ 1401408.28997129923664, 1151668.587228555465117 ] } },
{ "type": "Feature", "properties": { }, "geometry": { "type": "Point", "coordinates": [ 1399294.930087198503315, 1151647.6234489264898 ] } },
{ "type": "Feature", "properties": { }, "geometry": { "type": "Point", "coordinates": [ 1399148.538641126127914, 1151651.192126100417227 ] } },
{ "type": "Feature", "properties": { }, "geometry": { "type": "Point", "coordinates": [ 1398496.28556820936501, 1151644.158119775354862 ] } },
{ "type": "Feature", "properties": { }, "geometry": { "type": "Point", "coordinates": [ 1401150.202891912311316, 1151686.063896971289068 ] } },
{ "type": "Feature", "properties": { }, "geometry": { "type": "Point", "coordinates": [ 1399070.689934076974168, 1151660.865511290729046 ] } },
{ "type": "Feature", "properties": { }, "geometry": { "type": "Point", "coordinates": [ 1398237.365135118365288, 1151648.385042619192973 ] } },
{ "type": "Feature", "properties": { }, "geometry": { "type": "Point", "coordinates": [ 1398561.570206830976531, 1151661.478310958947986 ] } },
{ "type": "Feature", "properties": { }, "geometry": { "type": "Point", "coordinates": [ 1399072.87157302768901, 1151673.46916978340596 ] } },
{ "type": "Feature", "properties": { }, "geometry": { "type": "Point", "coordinates": [ 1399012.573873369256034, 1151676.72968476661481 ] } },
{ "type": "Feature", "properties": { }, "geometry": { "type": "Point", "coordinates": [ 1400892.076980554498732, 1151700.230129018193111 ] } },
{ "type": "Feature", "properties": { }, "geometry": { "type": "Point", "coordinates": [ 1398243.708125722594559, 1151668.981748980237171 ] } },
{ "type": "Feature", "properties": { }, "geometry": { "type": "Point", "coordinates": [ 1401514.535749340662733, 1151710.222567430930212 ] } },
{ "type": "Feature", "properties": { }, "geometry": { "type": "Point", "coordinates": [ 1396613.788418025244027, 1151654.384125996846706 ] } },
{ "type": "Feature", "properties": { }, "geometry": { "type": "Point", "coordinates": [ 1400691.451235237531364, 1151703.820885682245716 ] } },
{ "type": "Feature", "properties": { }, "geometry": { "type": "Point", "coordinates": [ 1398805.230001, 1151685.537138647167012 ] } },
{ "type": "Feature", "properties": { }, "geometry": { "type": "Point", "coordinates": [ 1396917.621649546315894, 1151664.589042322477326 ] } },
{ "type": "Feature", "properties": { }, "geometry": { "type": "Point", "coordinates": [ 1398409.956480443710461, 1151682.197256470797583 ] } },
{ "type": "Feature", "properties": { }, "geometry": { "type": "Point", "coordinates": [ 1398622.864354471443221, 1151685.37137429555878 ] } },
{ "type": "Feature", "properties": { }, "geometry": { "type": "Point", "coordinates": [ 1398188.304168296977878, 1151684.877922844840214 ] } },
{ "type": "Feature", "properties": { }, "geometry": { "type": "Point", "coordinates": [ 1400409.532289009075612, 1151712.410416134167463 ] } },
{ "type": "Feature", "properties": { }, "geometry": { "type": "Point", "coordinates": [ 1397984.919721332611516, 1151684.46415547747165 ] } },
{ "type": "Feature", "properties": { }, "geometry": { "type": "Point", "coordinates": [ 1397793.778571108123288, 1151687.504826229531318 ] } },
{ "type": "Feature", "properties": { }, "geometry": { "type": "Point", "coordinates": [ 1397736.902066129026935, 1151693.453690794063732 ] } },
{ "type": "Feature", "properties": { }, "geometry": { "type": "Point", "coordinates": [ 1397425.033487886423245, 1151691.759907859144732 ] } },
{ "type": "Feature", "properties": { }, "geometry": { "type": "Point", "coordinates": [ 1400915.626907679019496, 1151742.875717844581231 ] } },
{ "type": "Feature", "properties": { }, "geometry": { "type": "Point", "coordinates": [ 1399714.281649684533477, 1151738.630854541901499 ] } },
{ "type": "Feature", "properties": { }, "geometry": { "type": "Point", "coordinates": [ 1399073.539482927648351, 1151730.40867532347329 ] } },
{ "type": "Feature", "properties": { }, "geometry": { "type": "Point", "coordinates": [ 1399005.814564820611849, 1151736.229538331041113 ] } },
{ "type": "Feature", "properties": { }, "geometry": { "type": "Point", "coordinates": [ 1398805.23541786824353, 1151743.792818637331948 ] } },
{ "type": "Feature", "properties": { }, "geometry": { "type": "Point", "coordinates": [ 1399076.709803466452286, 1151769.503824862185866 ] } },
{ "type": "Feature", "properties": { }, "geometry": { "type": "Point", "coordinates": [ 1399008.306859538890421, 1151775.316687772748992 ] } },
{ "type": "Feature", "properties": { }, "geometry": { "type": "Point", "coordinates": [ 1396611.671977569116279, 1151762.926438400521874 ] } },
{ "type": "Feature", "properties": { }, "geometry": { "type": "Point", "coordinates": [ 1398406.383025221992284, 1151782.116434121970087 ] } },
{ "type": "Feature", "properties": { }, "geometry": { "type": "Point", "coordinates": [ 1396917.554819339886308, 1151774.479529565898702 ] } },
{ "type": "Feature", "properties": { }, "geometry": { "type": "Point", "coordinates": [ 1398192.890322103863582, 1151786.879363484680653 ] } },
{ "type": "Feature", "properties": { }, "geometry": { "type": "Point", "coordinates": [ 1398407.231911714654416, 1151796.69035424105823 ] } },
{ "type": "Feature", "properties": { }, "geometry": { "type": "Point", "coordinates": [ 1402102.480399776482955, 1151840.952971777878702 ] } },
{ "type": "Feature", "properties": { }, "geometry": { "type": "Point", "coordinates": [ 1397388.868194916052744, 1151787.322557197418064 ] } },
{ "type": "Feature", "properties": { }, "geometry": { "type": "Point", "coordinates": [ 1398448.630318735260516, 1151800.488796544726938 ] } },
{ "type": "Feature", "properties": { }, "geometry": { "type": "Point", "coordinates": [ 1398186.444018848938867, 1151815.269115281756967 ] } },
{ "type": "Feature", "properties": { }, "geometry": { "type": "Point", "coordinates": [ 1398448.894376137526706, 1151822.999763851286843 ] } },
{ "type": "Feature", "properties": { }, "geometry": { "type": "Point", "coordinates": [ 1398246.156889416975901, 1151819.94564748601988 ] } },
{ "type": "Feature", "properties": { }, "geometry": { "type": "Point", "coordinates": [ 1399714.160454718861729, 1151843.886730869067833 ] } },
{ "type": "Feature", "properties": { }, "geometry": { "type": "Point", "coordinates": [ 1402237.811390551738441, 1151876.973529373295605 ] } },
{ "type": "Feature", "properties": { }, "geometry": { "type": "Point", "coordinates": [ 1402114.325260886456817, 1151868.234551654430106 ] } },
{ "type": "Feature", "properties": { }, "geometry": { "type": "Point", "coordinates": [ 1401811.28655109857209, 1151867.968944531865418 ] } },
{ "type": "Feature", "properties": { }, "geometry": { "type": "Point", "coordinates": [ 1400612.575732444180176, 1151857.135208880994469 ] } },
{ "type": "Feature", "properties": { }, "geometry": { "type": "Point", "coordinates": [ 1402134.088972805067897, 1151877.073689034208655 ] } },
{ "type": "Feature", "properties": { }, "geometry": { "type": "Point", "coordinates": [ 1401205.817259795730934, 1151861.486944920150563 ] } },
{ "type": "Feature", "properties": { }, "geometry": { "type": "Point", "coordinates": [ 1400256.635475869756192, 1151854.921419621678069 ] } },
{ "type": "Feature", "properties": { }, "geometry": { "type": "Point", "coordinates": [ 1400003.046052612364292, 1151851.267295959405601 ] } },
{ "type": "Feature", "properties": { }, "geometry": { "type": "Point", "coordinates": [ 1400916.986026661470532, 1151858.740990745835006 ] } },
{ "type": "Feature", "properties": { }, "geometry": { "type": "Point", "coordinates": [ 1399738.67811377486214, 1151853.443956203758717 ] } },
{ "type": "Feature", "properties": { }, "geometry": { "type": "Point", "coordinates": [ 1397398.826540054054931, 1151827.159794982988387 ] } },
{ "type": "Feature", "properties": { }, "geometry": { "type": "Point", "coordinates": [ 1398221.318458672845736, 1151840.836436645127833 ] } },
{ "type": "Feature", "properties": { }, "geometry": { "type": "Point", "coordinates": [ 1397954.152986217522994, 1151835.6981364893727 ] } },
{ "type": "Feature", "properties": { }, "geometry": { "type": "Point", "coordinates": [ 1398445.760538043221459, 1151844.8086433976423 ] } },
{ "type": "Feature", "properties": { }, "geometry": { "type": "Point", "coordinates": [ 1398239.632922220276669, 1151841.714526545954868 ] } },
{ "type": "Feature", "properties": { }, "geometry": { "type": "Point", "coordinates": [ 1398805.800015117274597, 1151849.718782335519791 ] } },
{ "type": "Feature", "properties": { }, "geometry": { "type": "Point", "coordinates": [ 1398163.023770899046212, 1151841.472602825146168 ] } },
{ "type": "Feature", "properties": { }, "geometry": { "type": "Point", "coordinates": [ 1398702.747856797184795, 1151849.164854820119217 ] } },
{ "type": "Feature", "properties": { }, "geometry": { "type": "Point", "coordinates": [ 1399414.667201916920021, 1151856.902869707439095 ] } },
{ "type": "Feature", "properties": { }, "geometry": { "type": "Point", "coordinates": [ 1399182.805670492118225, 1151856.153098253300413 ] } },
{ "type": "Feature", "properties": { }, "geometry": { "type": "Point", "coordinates": [ 1399692.681087500182912, 1151862.169171419925988 ] } },
{ "type": "Feature", "properties": { }, "geometry": { "type": "Point", "coordinates": [ 1399013.306981763802469, 1151854.815161202801391 ] } },
{ "type": "Feature", "properties": { }, "geometry": { "type": "Point", "coordinates": [ 1396710.723528987262398, 1151826.984743512235582 ] } },
{ "type": "Feature", "properties": { }, "geometry": { "type": "Point", "coordinates": [ 1400334.474066998343915, 1151902.179539874196053 ] } },
{ "type": "Feature", "properties": { }, "geometry": { "type": "Point", "coordinates": [ 1400003.035936691565439, 1151908.198801402235404 ] } },
{ "type": "Feature", "properties": { }, "geometry": { "type": "Point", "coordinates": [ 1401518.017443461576477, 1151949.244073341600597 ] } },
{ "type": "Feature", "properties": { }, "geometry": { "type": "Point", "coordinates": [ 1400918.570371075067669, 1151993.806794584961608 ] } },
{ "type": "Feature", "properties": { }, "geometry": { "type": "Point", "coordinates": [ 1396558.380479361396283, 1151958.910350717836991 ] } },
{ "type": "Feature", "properties": { }, "geometry": { "type": "Point", "coordinates": [ 1398727.952025882899761, 1152032.835032949224114 ] } },
{ "type": "Feature", "properties": { }, "geometry": { "type": "Point", "coordinates": [ 1398900.178350681439042, 1152035.529144936008379 ] } },
{ "type": "Feature", "properties": { }, "geometry": { "type": "Point", "coordinates": [ 1398479.13984894589521, 1152031.885259062750265 ] } },
{ "type": "Feature", "properties": { }, "geometry": { "type": "Point", "coordinates": [ 1397959.565445149084553, 1152123.730100850341842 ] } },
{ "type": "Feature", "properties": { }, "geometry": { "type": "Point", "coordinates": [ 1398165.910520009230822, 1152145.362661366118118 ] } },
{ "type": "Feature", "properties": { }, "geometry": { "type": "Point", "coordinates": [ 1399699.206490326672792, 1152187.286023206310347 ] } },
{ "type": "Feature", "properties": { }, "geometry": { "type": "Point", "coordinates": [ 1402121.246749816462398, 1152227.117854400770739 ] } },
{ "type": "Feature", "properties": { }, "geometry": { "type": "Point", "coordinates": [ 1401818.862766666570678, 1152224.873985554091632 ] } },
{ "type": "Feature", "properties": { }, "geometry": { "type": "Point", "coordinates": [ 1401521.910756474593654, 1152223.356204759562388 ] } },
{ "type": "Feature", "properties": { }, "geometry": { "type": "Point", "coordinates": [ 1401220.890591359930113, 1152221.790423381375149 ] } },
{ "type": "Feature", "properties": { }, "geometry": { "type": "Point", "coordinates": [ 1400921.210945097729564, 1152218.916467650327832 ] } },
{ "type": "Feature", "properties": { }, "geometry": { "type": "Point", "coordinates": [ 1400629.675375075545162, 1152216.800600360613316 ] } },
{ "type": "Feature", "properties": { }, "geometry": { "type": "Point", "coordinates": [ 1400339.503623088588938, 1152215.362820538925007 ] } },
{ "type": "Feature", "properties": { }, "geometry": { "type": "Point", "coordinates": [ 1400007.941230474971235, 1152210.788685687584803 ] } },
{ "type": "Feature", "properties": { }, "geometry": { "type": "Point", "coordinates": [ 1398168.73676967760548, 1152212.919563577510417 ] } },
{ "type": "Feature", "properties": { }, "geometry": { "type": "Point", "coordinates": [ 1398947.881634150166065, 1152230.05672265519388 ] } },
{ "type": "Feature", "properties": { }, "geometry": { "type": "Point", "coordinates": [ 1398552.615879987599328, 1152227.378927752841264 ] } },
{ "type": "Feature", "properties": { }, "geometry": { "type": "Point", "coordinates": [ 1398240.084808712825179, 1152227.00131926801987 ] } },
{ "type": "Feature", "properties": { }, "geometry": { "type": "Point", "coordinates": [ 1400339.969606739701703, 1152255.088056962238625 ] } },
{ "type": "Feature", "properties": { }, "geometry": { "type": "Point", "coordinates": [ 1396562.444653046550229, 1152247.588402157649398 ] } },
{ "type": "Feature", "properties": { }, "geometry": { "type": "Point", "coordinates": [ 1397961.409147912403569, 1152396.494057428790256 ] } },
{ "type": "Feature", "properties": { }, "geometry": { "type": "Point", "coordinates": [ 1400927.0529052359052, 1152485.769639349309728 ] } },
{ "type": "Feature", "properties": { }, "geometry": { "type": "Point", "coordinates": [ 1401526.854882228886709, 1152529.256525413598865 ] } },
{ "type": "Feature", "properties": { }, "geometry": { "type": "Point", "coordinates": [ 1400012.650014877319336, 1152554.419980846345425 ] } },
{ "type": "Feature", "properties": { }, "geometry": { "type": "Point", "coordinates": [ 1399702.807747701881453, 1152552.088110929355025 ] } },
{ "type": "Feature", "properties": { }, "geometry": { "type": "Point", "coordinates": [ 1399449.935182236135006, 1152551.752423733007163 ] } },
{ "type": "Feature", "properties": { }, "geometry": { "type": "Point", "coordinates": [ 1399256.035330364480615, 1152550.788570453878492 ] } },
{ "type": "Feature", "properties": { }, "geometry": { "type": "Point", "coordinates": [ 1398948.905166471144184, 1152548.488700926071033 ] } },
{ "type": "Feature", "properties": { }, "geometry": { "type": "Point", "coordinates": [ 1398542.829831151291728, 1152548.993340835673735 ] } },
{ "type": "Feature", "properties": { }, "geometry": { "type": "Point", "coordinates": [ 1397985.601336227729917, 1152551.686482690507546 ] } },
{ "type": "Feature", "properties": { }, "geometry": { "type": "Point", "coordinates": [ 1398212.724453303031623, 1152553.042340737301856 ] } },
{ "type": "Feature", "properties": { }, "geometry": { "type": "Point", "coordinates": [ 1397737.459418716840446, 1152550.082621627720073 ] } },
{ "type": "Feature", "properties": { }, "geometry": { "type": "Point", "coordinates": [ 1402126.998580565908924, 1152601.875251521589234 ] } },
{ "type": "Feature", "properties": { }, "geometry": { "type": "Point", "coordinates": [ 1401825.292623236309737, 1152599.639382772380486 ] } },
{ "type": "Feature", "properties": { }, "geometry": { "type": "Point", "coordinates": [ 1397602.52451404533349, 1152547.828514992026612 ] } },
{ "type": "Feature", "properties": { }, "geometry": { "type": "Point", "coordinates": [ 1397454.753717149375007, 1152549.394930150127038 ] } },
{ "type": "Feature", "properties": { }, "geometry": { "type": "Point", "coordinates": [ 1401219.176371689653024, 1152595.7977321583312 ] } },
{ "type": "Feature", "properties": { }, "geometry": { "type": "Point", "coordinates": [ 1401526.314301977166906, 1152598.759688959689811 ] } },
{ "type": "Feature", "properties": { }, "geometry": { "type": "Point", "coordinates": [ 1397157.778407775098458, 1152545.890887534478679 ] } },
{ "type": "Feature", "properties": { }, "geometry": { "type": "Point", "coordinates": [ 1396867.598889393964782, 1152543.791020439239219 ] } },
{ "type": "Feature", "properties": { }, "geometry": { "type": "Point", "coordinates": [ 1400926.978308635298163, 1152594.998039318714291 ] } },
{ "type": "Feature", "properties": { }, "geometry": { "type": "Point", "coordinates": [ 1400649.66574805509299, 1152591.725999524816871 ] } },
{ "type": "Feature", "properties": { }, "geometry": { "type": "Point", "coordinates": [ 1400345.941246052505448, 1152590.790305030997843 ] } },
{ "type": "Feature", "properties": { }, "geometry": { "type": "Point", "coordinates": [ 1396566.602023461600766, 1152544.211500882171094 ] } },
{ "type": "Feature", "properties": { }, "geometry": { "type": "Point", "coordinates": [ 1399878.789222129620612, 1152585.940325267845765 ] } },
{ "type": "Feature", "properties": { }, "geometry": { "type": "Point", "coordinates": [ 1399256.46248204447329, 1152587.203370508505031 ] } },
{ "type": "Feature", "properties": { }, "geometry": { "type": "Point", "coordinates": [ 1399665.982311225961894, 1152591.373342001345009 ] } },
{ "type": "Feature", "properties": { }, "geometry": { "type": "Point", "coordinates": [ 1401530.760660688625649, 1152688.8435586723499 ] } },
{ "type": "Feature", "properties": { }, "geometry": { "type": "Point", "coordinates": [ 1398949.772653093328699, 1152680.23606829950586 ] } },
{ "type": "Feature", "properties": { }, "geometry": { "type": "Point", "coordinates": [ 1398545.286361240083352, 1152700.619326615240425 ] } },
{ "type": "Feature", "properties": { }, "geometry": { "type": "Point", "coordinates": [ 1398701.24006634671241, 1152703.121436267159879 ] } },
{ "type": "Feature", "properties": { }, "geometry": { "type": "Point", "coordinates": [ 1400927.460542889777571, 1152809.490315712522715 ] } },
{ "type": "Feature", "properties": { }, "geometry": { "type": "Point", "coordinates": [ 1400668.485745039535686, 1152809.082627640571445 ] } },
{ "type": "Feature", "properties": { }, "geometry": { "type": "Point", "coordinates": [ 1400397.992274635005742, 1152809.201025187969208 ] } },
{ "type": "Feature", "properties": { }, "geometry": { "type": "Point", "coordinates": [ 1398951.77096592518501, 1152792.798904929310083 ] } },
{ "type": "Feature", "properties": { }, "geometry": { "type": "Point", "coordinates": [ 1398217.6786949778907, 1152802.0111559482757 ] } },
{ "type": "Feature", "properties": { }, "geometry": { "type": "Point", "coordinates": [ 1399260.425692605087534, 1152867.274287390056998 ] } },
{ "type": "Feature", "properties": { }, "geometry": { "type": "Point", "coordinates": [ 1398703.828625136520714, 1152866.002905699890107 ] } },
{ "type": "Feature", "properties": { }, "geometry": { "type": "Point", "coordinates": [ 1399672.422283716499805, 1152909.20723377703689 ] } },
{ "type": "Feature", "properties": { }, "geometry": { "type": "Point", "coordinates": [ 1400091.113702696748078, 1152943.937221126165241 ] } },
{ "type": "Feature", "properties": { }, "geometry": { "type": "Point", "coordinates": [ 1399884.401257783640176, 1152948.780151461949572 ] } },
{ "type": "Feature", "properties": { }, "geometry": { "type": "Point", "coordinates": [ 1400349.004272702615708, 1152967.501963583985344 ] } },
{ "type": "Feature", "properties": { }, "geometry": { "type": "Point", "coordinates": [ 1398704.199062530882657, 1152955.376687554875389 ] } },
{ "type": "Feature", "properties": { }, "geometry": { "type": "Point", "coordinates": [ 1401848.000516365515068, 1153032.852462315931916 ] } },
{ "type": "Feature", "properties": { }, "geometry": { "type": "Point", "coordinates": [ 1402136.16925646783784, 1153036.914590940577909 ] } },
{ "type": "Feature", "properties": { }, "geometry": { "type": "Point", "coordinates": [ 1401533.412068446865305, 1153030.464591718045995 ] } },
{ "type": "Feature", "properties": { }, "geometry": { "type": "Point", "coordinates": [ 1401234.410448005190119, 1153027.598636084236205 ] } },
{ "type": "Feature", "properties": { }, "geometry": { "type": "Point", "coordinates": [ 1400673.706393642816693, 1153022.968817441724241 ] } },
{ "type": "Feature", "properties": { }, "geometry": { "type": "Point", "coordinates": [ 1400933.382516496116295, 1153025.370767432497814 ] } },
{ "type": "Feature", "properties": { }, "geometry": { "type": "Point", "coordinates": [ 1400407.257778979139403, 1153021.148953751893714 ] } },
{ "type": "Feature", "properties": { }, "geometry": { "type": "Point", "coordinates": [ 1399454.763529892312363, 1153021.164300704142079 ] } },
{ "type": "Feature", "properties": { }, "geometry": { "type": "Point", "coordinates": [ 1397450.596868467051536, 1153004.136885834857821 ] } },
{ "type": "Feature", "properties": { }, "geometry": { "type": "Point", "coordinates": [ 1396871.617182528600097, 1153001.93941365997307 ] } },
{ "type": "Feature", "properties": { }, "geometry": { "type": "Point", "coordinates": [ 1397635.760048614349216, 1153011.61761058610864 ] } },
{ "type": "Feature", "properties": { }, "geometry": { "type": "Point", "coordinates": [ 1396568.586239134892821, 1153002.335893810959533 ] } },
{ "type": "Feature", "properties": { }, "geometry": { "type": "Point", "coordinates": [ 1398553.393041139002889, 1153044.952709534205496 ] } },
{ "type": "Feature", "properties": { }, "geometry": { "type": "Point", "coordinates": [ 1398954.541219122475013, 1153086.757654364453629 ] } },
{ "type": "Feature", "properties": { }, "geometry": { "type": "Point", "coordinates": [ 1398223.937690875725821, 1153162.210633144713938 ] } },
{ "type": "Feature", "properties": { }, "geometry": { "type": "Point", "coordinates": [ 1397749.319616533117369, 1153156.610565037699416 ] } },
{ "type": "Feature", "properties": { }, "geometry": { "type": "Point", "coordinates": [ 1399267.378247111802921, 1153228.805939231067896 ] } },
{ "type": "Feature", "properties": { }, "geometry": { "type": "Point", "coordinates": [ 1399676.313247202895582, 1153240.912957911379635 ] } },
{ "type": "Feature", "properties": { }, "geometry": { "type": "Point", "coordinates": [ 1399456.648414152674377, 1153239.645100935129449 ] } },
{ "type": "Feature", "properties": { }, "geometry": { "type": "Point", "coordinates": [ 1399889.244420413393527, 1153246.073337557259947 ] } },
{ "type": "Feature", "properties": { }, "geometry": { "type": "Point", "coordinates": [ 1400094.76390796341002, 1153255.118239775300026 ] } },
{ "type": "Feature", "properties": { }, "geometry": { "type": "Point", "coordinates": [ 1398554.95173684344627, 1153235.625844268593937 ] } },
{ "type": "Feature", "properties": { }, "geometry": { "type": "Point", "coordinates": [ 1399441.527570326812565, 1153279.848422394366935 ] } },
{ "type": "Feature", "properties": { }, "geometry": { "type": "Point", "coordinates": [ 1397432.638027340639383, 1153264.751268664840609 ] } },
{ "type": "Feature", "properties": { }, "geometry": { "type": "Point", "coordinates": [ 1396571.801526327151805, 1153276.440025131683797 ] } },
{ "type": "Feature", "properties": { }, "geometry": { "type": "Point", "coordinates": [ 1400352.69872680795379, 1153340.249098591739312 ] } },
{ "type": "Feature", "properties": { }, "geometry": { "type": "Point", "coordinates": [ 1397166.764125846326351, 1153311.925863230368122 ] } },
{ "type": "Feature", "properties": { }, "geometry": { "type": "Point", "coordinates": [ 1400938.870289843296632, 1153377.617197246756405 ] } },
{ "type": "Feature", "properties": { }, "geometry": { "type": "Point", "coordinates": [ 1401538.524705346673727, 1153408.524425110314041 ] } },
{ "type": "Feature", "properties": { }, "geometry": { "type": "Point", "coordinates": [ 1397616.893257183022797, 1153368.210647814208642 ] } },
{ "type": "Feature", "properties": { }, "geometry": { "type": "Point", "coordinates": [ 1399289.036959211342037, 1153399.194371399004012 ] } },
{ "type": "Feature", "properties": { }, "geometry": { "type": "Point", "coordinates": [ 1400097.937295843614265, 1153410.062662020791322 ] } },
{ "type": "Feature", "properties": { }, "geometry": { "type": "Point", "coordinates": [ 1399440.236717180348933, 1153400.978393096011132 ] } },
{ "type": "Feature", "properties": { }, "geometry": { "type": "Point", "coordinates": [ 1398561.530786614399403, 1153391.934441548073664 ] } },
{ "type": "Feature", "properties": { }, "geometry": { "type": "Point", "coordinates": [ 1399823.336838545277715, 1153406.822622615844011 ] } },
{ "type": "Feature", "properties": { }, "geometry": { "type": "Point", "coordinates": [ 1399556.202431666664779, 1153404.332671554991975 ] } },
{ "type": "Feature", "properties": { }, "geometry": { "type": "Point", "coordinates": [ 1398957.497865780256689, 1153396.606498369015753 ] } },
{ "type": "Feature", "properties": { }, "geometry": { "type": "Point", "coordinates": [ 1400352.890537136001512, 1153414.394873151322827 ] } },
{ "type": "Feature", "properties": { }, "geometry": { "type": "Point", "coordinates": [ 1398228.658940725028515, 1153391.316830144496635 ] } },
{ "type": "Feature", "properties": { }, "geometry": { "type": "Point", "coordinates": [ 1401828.950398815330118, 1153489.404677681159228 ] } },
{ "type": "Feature", "properties": { }, "geometry": { "type": "Point", "coordinates": [ 1400352.248993759974837, 1153475.290902139386162 ] } },
{ "type": "Feature", "properties": { }, "geometry": { "type": "Point", "coordinates": [ 1401562.532849727896973, 1153490.233163086231798 ] } },
{ "type": "Feature", "properties": { }, "geometry": { "type": "Point", "coordinates": [ 1401258.785048542777076, 1153487.311206771293655 ] } },
{ "type": "Feature", "properties": { }, "geometry": { "type": "Point", "coordinates": [ 1400938.764627665979788, 1153484.197248121490702 ] } },
{ "type": "Feature", "properties": { }, "geometry": { "type": "Point", "coordinates": [ 1400644.516954361926764, 1153482.049380442360416 ] } },
{ "type": "Feature", "properties": { }, "geometry": { "type": "Point", "coordinates": [ 1402140.234147967537865, 1153499.03550780354999 ] } },
{ "type": "Feature", "properties": { }, "geometry": { "type": "Point", "coordinates": [ 1397168.371769442688674, 1153448.977928890613839 ] } },
{ "type": "Feature", "properties": { }, "geometry": { "type": "Point", "coordinates": [ 1401538.31808004505001, 1153506.497341426787898 ] } },
{ "type": "Feature", "properties": { }, "geometry": { "type": "Point", "coordinates": [ 1396573.952817516168579, 1153459.838199952617288 ] } },
{ "type": "Feature", "properties": { }, "geometry": { "type": "Point", "coordinates": [ 1400939.114115404430777, 1153513.991175438975915 ] } },
{ "type": "Feature", "properties": { }, "geometry": { "type": "Point", "coordinates": [ 1399768.458646398037672, 1153525.334323810180649 ] } },
{ "type": "Feature", "properties": { }, "geometry": { "type": "Point", "coordinates": [ 1399444.025999727658927, 1153550.634117249166593 ] } },
{ "type": "Feature", "properties": { }, "geometry": { "type": "Point", "coordinates": [ 1399443.166997314430773, 1153592.991702572908252 ] } },
{ "type": "Feature", "properties": { }, "geometry": { "type": "Point", "coordinates": [ 1397170.867131502134725, 1153603.914351038634777 ] } },
{ "type": "Feature", "properties": { }, "geometry": { "type": "Point", "coordinates": [ 1401542.511215089587495, 1153690.581603812985122 ] } },
{ "type": "Feature", "properties": { }, "geometry": { "type": "Point", "coordinates": [ 1401253.695514743681997, 1153689.159824186004698 ] } },
{ "type": "Feature", "properties": { }, "geometry": { "type": "Point", "coordinates": [ 1401047.637796468567103, 1153692.024492797907442 ] } },
{ "type": "Feature", "properties": { }, "geometry": { "type": "Point", "coordinates": [ 1398967.454579206649214, 1153667.480194293893874 ] } },
{ "type": "Feature", "properties": { }, "geometry": { "type": "Point", "coordinates": [ 1401228.693989721825346, 1153696.146780597046018 ] } },
{ "type": "Feature", "properties": { }, "geometry": { "type": "Point", "coordinates": [ 1398670.502569014905021, 1153665.962413499364629 ] } },
{ "type": "Feature", "properties": { }, "geometry": { "type": "Point", "coordinates": [ 1398454.220098672900349, 1153664.072469735750929 ] } },
{ "type": "Feature", "properties": { }, "geometry": { "type": "Point", "coordinates": [ 1398232.521188161103055, 1153662.780612467555329 ] } },
{ "type": "Feature", "properties": { }, "geometry": { "type": "Point", "coordinates": [ 1402171.421703998697922, 1153730.439970418810844 ] } },
{ "type": "Feature", "properties": { }, "geometry": { "type": "Point", "coordinates": [ 1400359.812026066007093, 1153773.278175897663459 ] } },
{ "type": "Feature", "properties": { }, "geometry": { "type": "Point", "coordinates": [ 1396878.188269823323935, 1153735.508112651761621 ] } },
{ "type": "Feature", "properties": { }, "geometry": { "type": "Point", "coordinates": [ 1399447.968260632129386, 1153771.12517959321849 ] } },
{ "type": "Feature", "properties": { }, "geometry": { "type": "Point", "coordinates": [ 1400090.82993518630974, 1153786.65431911428459 ] } },
{ "type": "Feature", "properties": { }, "geometry": { "type": "Point", "coordinates": [ 1399772.905722924508154, 1153788.861058946000412 ] } },
{ "type": "Feature", "properties": { }, "geometry": { "type": "Point", "coordinates": [ 1399894.303410368738696, 1153792.941425456898287 ] } },
{ "type": "Feature", "properties": { }, "geometry": { "type": "Point", "coordinates": [ 1402044.219974490115419, 1153867.296192140318453 ] } },
{ "type": "Feature", "properties": { }, "geometry": { "type": "Point", "coordinates": [ 1399447.427680380409583, 1153840.628343139076605 ] } },
{ "type": "Feature", "properties": { }, "geometry": { "type": "Point", "coordinates": [ 1398238.779466243926436, 1153849.537224240833893 ] } },
{ "type": "Feature", "properties": { }, "geometry": { "type": "Point", "coordinates": [ 1400946.447223225841299, 1153907.965103692375124 ] } },
{ "type": "Feature", "properties": { }, "geometry": { "type": "Point", "coordinates": [ 1402099.908938973909244, 1153933.490840120008215 ] } },
{ "type": "Feature", "properties": { }, "geometry": { "type": "Point", "coordinates": [ 1396577.435229452094063, 1153872.302571286680177 ] } },
{ "type": "Feature", "properties": { }, "geometry": { "type": "Point", "coordinates": [ 1399448.359647682635114, 1153920.078815985703841 ] } },
{ "type": "Feature", "properties": { }, "geometry": { "type": "Point", "coordinates": [ 1400942.079246271401644, 1153997.944972140248865 ] } },
{ "type": "Feature", "properties": { }, "geometry": { "type": "Point", "coordinates": [ 1397626.064650899963453, 1153976.69285265612416 ] } },
{ "type": "Feature", "properties": { }, "geometry": { "type": "Point", "coordinates": [ 1401941.448124175425619, 1154064.020271902205423 ] } },
{ "type": "Feature", "properties": { }, "geometry": { "type": "Point", "coordinates": [ 1401544.989412649534643, 1154075.230309553444386 ] } },
{ "type": "Feature", "properties": { }, "geometry": { "type": "Point", "coordinates": [ 1400360.610332955373451, 1154072.509623230667785 ] } },
{ "type": "Feature", "properties": { }, "geometry": { "type": "Point", "coordinates": [ 1400115.258182668592781, 1154077.558635294204578 ] } },
{ "type": "Feature", "properties": { }, "geometry": { "type": "Point", "coordinates": [ 1399614.976090271491557, 1154080.26169804809615 ] } },
{ "type": "Feature", "properties": { }, "geometry": { "type": "Point", "coordinates": [ 1399910.579815216595307, 1154082.425565921934322 ] } },
{ "type": "Feature", "properties": { }, "geometry": { "type": "Point", "coordinates": [ 1399450.239115075208247, 1154080.303936226293445 ] } },
{ "type": "Feature", "properties": { }, "geometry": { "type": "Point", "coordinates": [ 1398837.169395125005394, 1154119.409957334166393 ] } },
{ "type": "Feature", "properties": { }, "geometry": { "type": "Point", "coordinates": [ 1400944.613440301967785, 1154156.191830656956881 ] } },
{ "type": "Feature", "properties": { }, "geometry": { "type": "Point", "coordinates": [ 1399134.300032383296639, 1154136.155745424097404 ] } },
{ "type": "Feature", "properties": { }, "geometry": { "type": "Point", "coordinates": [ 1400533.753092267783359, 1154153.330033516744152 ] } },
{ "type": "Feature", "properties": { }, "geometry": { "type": "Point", "coordinates": [ 1401944.108930039452389, 1154175.266934082144871 ] } },
{ "type": "Feature", "properties": { }, "geometry": { "type": "Point", "coordinates": [ 1398242.797041563782841, 1154134.242752038408071 ] } },
{ "type": "Feature", "properties": { }, "geometry": { "type": "Point", "coordinates": [ 1401797.707368046510965, 1154235.76711669866927 ] } },
{ "type": "Feature", "properties": { }, "geometry": { "type": "Point", "coordinates": [ 1402155.790431600995362, 1154247.274128081975505 ] } },
{ "type": "Feature", "properties": { }, "geometry": { "type": "Point", "coordinates": [ 1398837.553015781566501, 1154267.701506453333423 ] } },
{ "type": "Feature", "properties": { }, "geometry": { "type": "Point", "coordinates": [ 1399453.0039514049422, 1154316.007005671272054 ] } },
{ "type": "Feature", "properties": { }, "geometry": { "type": "Point", "coordinates": [ 1400362.992266443558037, 1154333.364008979639038 ] } },
{ "type": "Feature", "properties": { }, "geometry": { "type": "Point", "coordinates": [ 1401776.298616190440953, 1154433.451208136277273 ] } },
{ "type": "Feature", "properties": { }, "geometry": { "type": "Point", "coordinates": [ 1401683.502275513485074, 1154440.30024209106341 ] } },
{ "type": "Feature", "properties": { }, "geometry": { "type": "Point", "coordinates": [ 1401547.553040544968098, 1154467.161975304828957 ] } },
{ "type": "Feature", "properties": { }, "geometry": { "type": "Point", "coordinates": [ 1400949.588631632737815, 1154464.740500405663624 ] } },
{ "type": "Feature", "properties": { }, "geometry": { "type": "Point", "coordinates": [ 1399139.259690925711766, 1154443.380240625469014 ] } },
{ "type": "Feature", "properties": { }, "geometry": { "type": "Point", "coordinates": [ 1398837.592565567232668, 1154444.454808244947344 ] } },
{ "type": "Feature", "properties": { }, "geometry": { "type": "Point", "coordinates": [ 1398248.419193138601258, 1154440.151072789682075 ] } },
{ "type": "Feature", "properties": { }, "geometry": { "type": "Point", "coordinates": [ 1400621.672659129835665, 1154482.055246073519811 ] } },
{ "type": "Feature", "properties": { }, "geometry": { "type": "Point", "coordinates": [ 1401077.306010498665273, 1154487.431311456486583 ] } },
{ "type": "Feature", "properties": { }, "geometry": { "type": "Point", "coordinates": [ 1400950.507415672997013, 1154485.273205988574773 ] } },
{ "type": "Feature", "properties": { }, "geometry": { "type": "Point", "coordinates": [ 1401490.223735176725313, 1154492.30337070976384 ] } },
{ "type": "Feature", "properties": { }, "geometry": { "type": "Point", "coordinates": [ 1400363.352587917353958, 1154479.669296277454123 ] } },
{ "type": "Feature", "properties": { }, "geometry": { "type": "Point", "coordinates": [ 1400152.486557745141909, 1154477.18126601842232 ] } },
{ "type": "Feature", "properties": { }, "geometry": { "type": "Point", "coordinates": [ 1399814.143906926736236, 1154472.52713019400835 ] } },
{ "type": "Feature", "properties": { }, "geometry": { "type": "Point", "coordinates": [ 1399171.383195496862754, 1154465.605125231202692 ] } },
{ "type": "Feature", "properties": { }, "geometry": { "type": "Point", "coordinates": [ 1401702.461349778342992, 1154496.131575710838661 ] } },
{ "type": "Feature", "properties": { }, "geometry": { "type": "Point", "coordinates": [ 1399496.165329905459657, 1154470.099259109701961 ] } },
{ "type": "Feature", "properties": { }, "geometry": { "type": "Point", "coordinates": [ 1401309.87663332070224, 1154490.837432102765888 ] } },
{ "type": "Feature", "properties": { }, "geometry": { "type": "Point", "coordinates": [ 1402158.997952399309725, 1154520.716172128915787 ] } },
{ "type": "Feature", "properties": { }, "geometry": { "type": "Point", "coordinates": [ 1401510.813034405466169, 1154513.730166387744248 ] } },
{ "type": "Feature", "properties": { }, "geometry": { "type": "Point", "coordinates": [ 1401840.333583163330331, 1154517.618213673587888 ] } },
{ "type": "Feature", "properties": { }, "geometry": { "type": "Point", "coordinates": [ 1401310.125157934613526, 1154512.02422486199066 ] } },
{ "type": "Feature", "properties": { }, "geometry": { "type": "Point", "coordinates": [ 1399137.722662692191079, 1154485.729825851973146 ] } },
{ "type": "Feature", "properties": { }, "geometry": { "type": "Point", "coordinates": [ 1398837.372757003642619, 1154483.509957297239453 ] } },
{ "type": "Feature", "properties": { }, "geometry": { "type": "Point", "coordinates": [ 1398534.981007459573448, 1154480.604001177009195 ] } },
{ "type": "Feature", "properties": { }, "geometry": { "type": "Point", "coordinates": [ 1397953.92841208842583, 1154475.072092341724783 ] } },
{ "type": "Feature", "properties": { }, "geometry": { "type": "Point", "coordinates": [ 1398248.199384575011209, 1154479.206221841741353 ] } },
{ "type": "Feature", "properties": { }, "geometry": { "type": "Point", "coordinates": [ 1397303.046923601068556, 1154469.378260758938268 ] } },
{ "type": "Feature", "properties": { }, "geometry": { "type": "Point", "coordinates": [ 1396915.89418010157533, 1154464.810205202782527 ] } },
{ "type": "Feature", "properties": { }, "geometry": { "type": "Point", "coordinates": [ 1397660.350998210720718, 1154472.270137486280873 ] } },
{ "type": "Feature", "properties": { }, "geometry": { "type": "Point", "coordinates": [ 1401483.293565955944359, 1154537.237304252572358 ] } },
{ "type": "Feature", "properties": { }, "geometry": { "type": "Point", "coordinates": [ 1400151.883846340235323, 1154541.387731374939904 ] } },
{ "type": "Feature", "properties": { }, "geometry": { "type": "Point", "coordinates": [ 1398821.682616875739768, 1154532.974500491051003 ] } },
{ "type": "Feature", "properties": { }, "geometry": { "type": "Point", "coordinates": [ 1401456.646283181617036, 1154577.304624057840556 ] } },
{ "type": "Feature", "properties": { }, "geometry": { "type": "Point", "coordinates": [ 1401256.737395655829459, 1154584.213817187584937 ] } },
{ "type": "Feature", "properties": { }, "geometry": { "type": "Point", "coordinates": [ 1399438.950170923490077, 1154562.765556337079033 ] } },
{ "type": "Feature", "properties": { }, "geometry": { "type": "Point", "coordinates": [ 1401673.95626708236523, 1154608.996495236176997 ] } },
{ "type": "Feature", "properties": { }, "geometry": { "type": "Point", "coordinates": [ 1402065.231530264019966, 1154618.247162292012945 ] } },
{ "type": "Feature", "properties": { }, "geometry": { "type": "Point", "coordinates": [ 1398821.289598113624379, 1154615.057322238106281 ] } },
{ "type": "Feature", "properties": { }, "geometry": { "type": "Point", "coordinates": [ 1399677.074679484125227, 1154635.084754131501541 ] } },
{ "type": "Feature", "properties": { }, "geometry": { "type": "Point", "coordinates": [ 1397303.515974593348801, 1154624.952769888797775 ] } },
{ "type": "Feature", "properties": { }, "geometry": { "type": "Point", "coordinates": [ 1401664.647949529346079, 1154682.368181159719825 ] } },
{ "type": "Feature", "properties": { }, "geometry": { "type": "Point", "coordinates": [ 1399910.696115047670901, 1154670.279064013622701 ] } },
{ "type": "Feature", "properties": { }, "geometry": { "type": "Point", "coordinates": [ 1400618.555071638664231, 1154678.631165590602905 ] } },
{ "type": "Feature", "properties": { }, "geometry": { "type": "Point", "coordinates": [ 1399680.806529930559918, 1154664.25659466162324 ] } },
{ "type": "Feature", "properties": { }, "geometry": { "type": "Point", "coordinates": [ 1398119.390729285310954, 1154652.453243326162919 ] } },
{ "type": "Feature", "properties": { }, "geometry": { "type": "Point", "coordinates": [ 1397306.911520563531667, 1154683.248450365383178 ] } },
{ "type": "Feature", "properties": { }, "geometry": { "type": "Point", "coordinates": [ 1399440.058415765408427, 1154715.03762919572182 ] } },
{ "type": "Feature", "properties": { }, "geometry": { "type": "Point", "coordinates": [ 1401361.006528336554766, 1154746.30903939367272 ] } },
{ "type": "Feature", "properties": { }, "geometry": { "type": "Point", "coordinates": [ 1399155.629292503930628, 1154740.809428375214338 ] } },
{ "type": "Feature", "properties": { }, "geometry": { "type": "Point", "coordinates": [ 1399159.055904050823301, 1154801.753457946702838 ] } },
{ "type": "Feature", "properties": { }, "geometry": { "type": "Point", "coordinates": [ 1396764.37743560038507, 1154782.766336129512638 ] } },
{ "type": "Feature", "properties": { }, "geometry": { "type": "Point", "coordinates": [ 1396690.464854772901163, 1154781.232238250318915 ] } },
{ "type": "Feature", "properties": { }, "geometry": { "type": "Point", "coordinates": [ 1396575.208231683820486, 1154780.534308983944356 ] } },
{ "type": "Feature", "properties": { }, "geometry": { "type": "Point", "coordinates": [ 1400888.979362310143188, 1154845.99684800254181 ] } },
{ "type": "Feature", "properties": { }, "geometry": { "type": "Point", "coordinates": [ 1401074.049345727078617, 1154845.532525469549 ] } },
{ "type": "Feature", "properties": { }, "geometry": { "type": "Point", "coordinates": [ 1400619.148384937783703, 1154844.799071100074798 ] } },
{ "type": "Feature", "properties": { }, "geometry": { "type": "Point", "coordinates": [ 1401100.663213398307562, 1154860.41044928599149 ] } },
{ "type": "Feature", "properties": { }, "geometry": { "type": "Point", "coordinates": [ 1401287.19021158060059, 1154868.569261505967006 ] } },
{ "type": "Feature", "properties": { }, "geometry": { "type": "Point", "coordinates": [ 1399440.925902387592942, 1154846.784996568923816 ] } },
{ "type": "Feature", "properties": { }, "geometry": { "type": "Point", "coordinates": [ 1401587.58671563398093, 1154874.761653702938929 ] } },
{ "type": "Feature", "properties": { }, "geometry": { "type": "Point", "coordinates": [ 1398692.28985031042248, 1154887.601434586104006 ] } },
{ "type": "Feature", "properties": { }, "geometry": { "type": "Point", "coordinates": [ 1398293.602901468519121, 1154882.235290102427825 ] } },
{ "type": "Feature", "properties": { }, "geometry": { "type": "Point", "coordinates": [ 1398823.826859485358, 1154889.153453461593017 ] } },
{ "type": "Feature", "properties": { }, "geometry": { "type": "Point", "coordinates": [ 1398463.818447988014668, 1154886.891663618385792 ] } },
{ "type": "Feature", "properties": { }, "geometry": { "type": "Point", "coordinates": [ 1396937.590092460392043, 1154869.54553187917918 ] } },
{ "type": "Feature", "properties": { }, "geometry": { "type": "Point", "coordinates": [ 1401896.686476308852434, 1154929.382418049033731 ] } },
{ "type": "Feature", "properties": { }, "geometry": { "type": "Point", "coordinates": [ 1398122.810292252805084, 1154886.178051047259942 ] } },
{ "type": "Feature", "properties": { }, "geometry": { "type": "Point", "coordinates": [ 1401066.876068760175258, 1154927.535346243530512 ] } },
{ "type": "Feature", "properties": { }, "geometry": { "type": "Point", "coordinates": [ 1401092.842976187355816, 1154945.05361905740574 ] } },
{ "type": "Feature", "properties": { }, "geometry": { "type": "Point", "coordinates": [ 1400564.021668176632375, 1154942.123979535419494 ] } },
{ "type": "Feature", "properties": { }, "geometry": { "type": "Point", "coordinates": [ 1397308.83523679501377, 1154905.039686964824796 ] } },
{ "type": "Feature", "properties": { }, "geometry": { "type": "Point", "coordinates": [ 1397686.244744667084888, 1154945.902541116112843 ] } },
{ "type": "Feature", "properties": { }, "geometry": { "type": "Point", "coordinates": [ 1399682.171783595578745, 1155011.820412976201624 ] } },
{ "type": "Feature", "properties": { }, "geometry": { "type": "Point", "coordinates": [ 1400154.450541577069089, 1155049.168669832870364 ] } },
{ "type": "Feature", "properties": { }, "geometry": { "type": "Point", "coordinates": [ 1400271.482601593015715, 1155085.635312075028196 ] } },
{ "type": "Feature", "properties": { }, "geometry": { "type": "Point", "coordinates": [ 1400153.599305558251217, 1155092.188342430163175 ] } },
{ "type": "Feature", "properties": { }, "geometry": { "type": "Point", "coordinates": [ 1400388.289436177583411, 1155102.901423379313201 ] } },
{ "type": "Feature", "properties": { }, "geometry": { "type": "Point", "coordinates": [ 1402203.543184694368392, 1155139.545691136270761 ] } },
{ "type": "Feature", "properties": { }, "geometry": { "type": "Point", "coordinates": [ 1396688.551058380398899, 1155080.4316851941403 ] } },
{ "type": "Feature", "properties": { }, "geometry": { "type": "Point", "coordinates": [ 1401459.943019471829757, 1155147.321766245411709 ] } },
{ "type": "Feature", "properties": { }, "geometry": { "type": "Point", "coordinates": [ 1400886.410839279647917, 1155147.174556670244783 ] } },
{ "type": "Feature", "properties": { }, "geometry": { "type": "Point", "coordinates": [ 1399160.835126133868471, 1155126.814309051958844 ] } },
{ "type": "Feature", "properties": { }, "geometry": { "type": "Point", "coordinates": [ 1397309.216507924720645, 1155110.924828800372779 ] } },
{ "type": "Feature", "properties": { }, "geometry": { "type": "Point", "coordinates": [ 1400936.701245908625424, 1155157.697872976073995 ] } },
{ "type": "Feature", "properties": { }, "geometry": { "type": "Point", "coordinates": [ 1399444.521742895012721, 1155153.33140430203639 ] } },
{ "type": "Feature", "properties": { }, "geometry": { "type": "Point", "coordinates": [ 1400518.615605674684048, 1155174.610692977206782 ] } },
{ "type": "Feature", "properties": { }, "geometry": { "type": "Point", "coordinates": [ 1401756.00496167386882, 1155188.548783268779516 ] } },
{ "type": "Feature", "properties": { }, "geometry": { "type": "Point", "coordinates": [ 1398126.548277381807566, 1155147.048436990939081 ] } },
{ "type": "Feature", "properties": { }, "geometry": { "type": "Point", "coordinates": [ 1400154.311464296653867, 1155210.693964329082519 ] } },
{ "type": "Feature", "properties": { }, "geometry": { "type": "Point", "coordinates": [ 1398465.341379063203931, 1155190.103634691098705 ] } },
{ "type": "Feature", "properties": { }, "geometry": { "type": "Point", "coordinates": [ 1398825.419688108144328, 1155198.324209997663274 ] } },
{ "type": "Feature", "properties": { }, "geometry": { "type": "Point", "coordinates": [ 1401100.514738011872396, 1155252.310114648193121 ] } },
{ "type": "Feature", "properties": { }, "geometry": { "type": "Point", "coordinates": [ 1396938.2462547281757, 1155214.453001001384109 ] } },
{ "type": "Feature", "properties": { }, "geometry": { "type": "Point", "coordinates": [ 1400872.190897179068998, 1155264.180001881206408 ] } },
{ "type": "Feature", "properties": { }, "geometry": { "type": "Point", "coordinates": [ 1400724.722989656496793, 1155291.567820714553818 ] } },
{ "type": "Feature", "properties": { }, "geometry": { "type": "Point", "coordinates": [ 1401179.070186932105571, 1155302.886671366402879 ] } },
{ "type": "Feature", "properties": { }, "geometry": { "type": "Point", "coordinates": [ 1397311.610906860092655, 1155257.254116390133277 ] } },
{ "type": "Feature", "properties": { }, "geometry": { "type": "Point", "coordinates": [ 1400786.149165998212993, 1155326.71636770456098 ] } },
{ "type": "Feature", "properties": { }, "geometry": { "type": "Point", "coordinates": [ 1401278.067373591242358, 1155362.310365561628714 ] } },
{ "type": "Feature", "properties": { }, "geometry": { "type": "Point", "coordinates": [ 1402072.066674961242825, 1155374.326828590128571 ] } },
{ "type": "Feature", "properties": { }, "geometry": { "type": "Point", "coordinates": [ 1400312.035907277371734, 1155364.151972389547154 ] } },
{ "type": "Feature", "properties": { }, "geometry": { "type": "Point", "coordinates": [ 1400421.907155773602426, 1155368.096337246242911 ] } },
{ "type": "Feature", "properties": { }, "geometry": { "type": "Point", "coordinates": [ 1399965.650143343256786, 1155367.346882682060823 ] } },
{ "type": "Feature", "properties": { }, "geometry": { "type": "Point", "coordinates": [ 1399685.656545057892799, 1155366.691191593883559 ] } },
{ "type": "Feature", "properties": { }, "geometry": { "type": "Point", "coordinates": [ 1396691.851775908842683, 1155361.818776525789872 ] } },
{ "type": "Feature", "properties": { }, "geometry": { "type": "Point", "coordinates": [ 1401331.574699124321342, 1155415.901355048641562 ] } },
{ "type": "Feature", "properties": { }, "geometry": { "type": "Point", "coordinates": [ 1398127.465429710689932, 1155398.617600713158026 ] } },
{ "type": "Feature", "properties": { }, "geometry": { "type": "Point", "coordinates": [ 1397903.747974525904283, 1155398.625917700352147 ] } },
{ "type": "Feature", "properties": { }, "geometry": { "type": "Point", "coordinates": [ 1397690.840100497938693, 1155395.451799875823781 ] } },
{ "type": "Feature", "properties": { }, "geometry": { "type": "Point", "coordinates": [ 1402033.66537828091532, 1155452.651208519935608 ] } },
{ "type": "Feature", "properties": { }, "geometry": { "type": "Point", "coordinates": [ 1401610.647163843037561, 1155453.617933270754293 ] } },
{ "type": "Feature", "properties": { }, "geometry": { "type": "Point", "coordinates": [ 1399163.745174426818267, 1155432.690629414049909 ] } },
{ "type": "Feature", "properties": { }, "geometry": { "type": "Point", "coordinates": [ 1399446.761531761381775, 1155459.861811840673909 ] } },
{ "type": "Feature", "properties": { }, "geometry": { "type": "Point", "coordinates": [ 1398702.00724114687182, 1155484.836155872093514 ] } },
{ "type": "Feature", "properties": { }, "geometry": { "type": "Point", "coordinates": [ 1398316.272680441616103, 1155485.580798700451851 ] } },
{ "type": "Feature", "properties": { }, "geometry": { "type": "Point", "coordinates": [ 1398828.166642122901976, 1155490.296697611687705 ] } },
{ "type": "Feature", "properties": { }, "geometry": { "type": "Point", "coordinates": [ 1398467.449139228323475, 1155485.378558576339856 ] } },
{ "type": "Feature", "properties": { }, "geometry": { "type": "Point", "coordinates": [ 1400692.15281937899999, 1155520.234012362780049 ] } },
{ "type": "Feature", "properties": { }, "geometry": { "type": "Point", "coordinates": [ 1396945.136678081238642, 1155570.687954652821645 ] } },
{ "type": "Feature", "properties": { }, "geometry": { "type": "Point", "coordinates": [ 1400670.218302244786173, 1155615.302576470654458 ] } },
{ "type": "Feature", "properties": { }, "geometry": { "type": "Point", "coordinates": [ 1397314.901508467737585, 1155595.572713164612651 ] } },
{ "type": "Feature", "properties": { }, "geometry": { "type": "Point", "coordinates": [ 1400156.77177954162471, 1155651.612088238587603 ] } },
{ "type": "Feature", "properties": { }, "geometry": { "type": "Point", "coordinates": [ 1401905.625596015248448, 1155691.444870102684945 ] } },
{ "type": "Feature", "properties": { }, "geometry": { "type": "Point", "coordinates": [ 1396693.040752033703029, 1155636.560994828585535 ] } },
{ "type": "Feature", "properties": { }, "geometry": { "type": "Point", "coordinates": [ 1401201.94352386565879, 1155692.40999094163999 ] } },
{ "type": "Feature", "properties": { }, "geometry": { "type": "Point", "coordinates": [ 1401460.644148393301293, 1155727.238217149861157 ] } },
{ "type": "Feature", "properties": { }, "geometry": { "type": "Point", "coordinates": [ 1400020.212066773790866, 1155742.01819953462109 ] } },
{ "type": "Feature", "properties": { }, "geometry": { "type": "Point", "coordinates": [ 1399690.707050804281607, 1155739.454326796345413 ] } },
{ "type": "Feature", "properties": { }, "geometry": { "type": "Point", "coordinates": [ 1399450.163212414132431, 1155749.856037730583921 ] } },
{ "type": "Feature", "properties": { }, "geometry": { "type": "Point", "coordinates": [ 1399164.74540756479837, 1155749.136345863807946 ] } },
{ "type": "Feature", "properties": { }, "geometry": { "type": "Point", "coordinates": [ 1398830.220037529012188, 1155780.937010580673814 ] } },
{ "type": "Feature", "properties": { }, "geometry": { "type": "Point", "coordinates": [ 1402251.623758055036888, 1155828.588461547158659 ] } },
{ "type": "Feature", "properties": { }, "geometry": { "type": "Point", "coordinates": [ 1401031.200580356409773, 1155816.174548235489056 ] } },
{ "type": "Feature", "properties": { }, "geometry": { "type": "Point", "coordinates": [ 1398470.561113769887015, 1155808.469148055184633 ] } },
{ "type": "Feature", "properties": { }, "geometry": { "type": "Point", "coordinates": [ 1400533.987845374038443, 1155849.365625969832763 ] } },
{ "type": "Feature", "properties": { }, "geometry": { "type": "Point", "coordinates": [ 1400559.939220013096929, 1155865.559724236372858 ] } },
{ "type": "Feature", "properties": { }, "geometry": { "type": "Point", "coordinates": [ 1401746.631967359222472, 1155892.13955270498991 ] } },
{ "type": "Feature", "properties": { }, "geometry": { "type": "Point", "coordinates": [ 1401782.815860459115356, 1155913.750350620830432 ] } },
{ "type": "Feature", "properties": { }, "geometry": { "type": "Point", "coordinates": [ 1401035.980894017964602, 1155934.728170718066394 ] } },
{ "type": "Feature", "properties": { }, "geometry": { "type": "Point", "coordinates": [ 1396947.032396076945588, 1155905.680114864138886 ] } },
{ "type": "Feature", "properties": { }, "geometry": { "type": "Point", "coordinates": [ 1401875.617618003627285, 1155965.1569966559764 ] } },
{ "type": "Feature", "properties": { }, "geometry": { "type": "Point", "coordinates": [ 1396696.24050643760711, 1155909.340951601974666 ] } },
{ "type": "Feature", "properties": { }, "geometry": { "type": "Point", "coordinates": [ 1401315.255284985527396, 1155989.659018056932837 ] } },
{ "type": "Feature", "properties": { }, "geometry": { "type": "Point", "coordinates": [ 1396946.797054725233465, 1155943.411089368863031 ] } },
{ "type": "Feature", "properties": { }, "geometry": { "type": "Point", "coordinates": [ 1397742.160174130229279, 1155956.105639865854755 ] } },
{ "type": "Feature", "properties": { }, "geometry": { "type": "Point", "coordinates": [ 1397319.742321571102366, 1155950.45949197653681 ] } },
{ "type": "Feature", "properties": { }, "geometry": { "type": "Point", "coordinates": [ 1396696.28475527651608, 1155970.907067960593849 ] } },
{ "type": "Feature", "properties": { }, "geometry": { "type": "Point", "coordinates": [ 1400860.173347603762522, 1156031.291149108437821 ] } },
{ "type": "Feature", "properties": { }, "geometry": { "type": "Point", "coordinates": [ 1397896.61568297422491, 1156004.267771112499759 ] } },
{ "type": "Feature", "properties": { }, "geometry": { "type": "Point", "coordinates": [ 1399454.173021339811385, 1156033.899478254374117 ] } },
{ "type": "Feature", "properties": { }, "geometry": { "type": "Point", "coordinates": [ 1400417.070649559143931, 1156053.866750973043963 ] } },
{ "type": "Feature", "properties": { }, "geometry": { "type": "Point", "coordinates": [ 1402100.194793416419998, 1156096.233959768200293 ] } },
{ "type": "Feature", "properties": { }, "geometry": { "type": "Point", "coordinates": [ 1398831.595407114597037, 1156071.569323452422395 ] } },
{ "type": "Feature", "properties": { }, "geometry": { "type": "Point", "coordinates": [ 1398186.800618223147467, 1156064.623318197904155 ] } },
{ "type": "Feature", "properties": { }, "geometry": { "type": "Point", "coordinates": [ 1398472.257255043368787, 1156068.653446433134377 ] } },
{ "type": "Feature", "properties": { }, "geometry": { "type": "Point", "coordinates": [ 1398090.528718107845634, 1156064.149391655577347 ] } },
{ "type": "Feature", "properties": { }, "geometry": { "type": "Point", "coordinates": [ 1398891.97077071480453, 1156074.929681206820533 ] } },
{ "type": "Feature", "properties": { }, "geometry": { "type": "Point", "coordinates": [ 1399694.753342174459249, 1156084.40179640520364 ] } },
{ "type": "Feature", "properties": { }, "geometry": { "type": "Point", "coordinates": [ 1400156.504458716139197, 1156091.174037211341783 ] } },
{ "type": "Feature", "properties": { }, "geometry": { "type": "Point", "coordinates": [ 1399452.705890653887764, 1156082.207848944235593 ] } },
{ "type": "Feature", "properties": { }, "geometry": { "type": "Point", "coordinates": [ 1400380.954304480692372, 1156095.808331237407401 ] } },
{ "type": "Feature", "properties": { }, "geometry": { "type": "Point", "coordinates": [ 1399934.119755989639089, 1156089.212092571891844 ] } },
{ "type": "Feature", "properties": { }, "geometry": { "type": "Point", "coordinates": [ 1399600.531052308855578, 1156085.276044702157378 ] } },
{ "type": "Feature", "properties": { }, "geometry": { "type": "Point", "coordinates": [ 1399245.923548192949966, 1156081.091993816429749 ] } },
{ "type": "Feature", "properties": { }, "geometry": { "type": "Point", "coordinates": [ 1399167.958345230668783, 1156080.834069901145995 ] } },
{ "type": "Feature", "properties": { }, "geometry": { "type": "Point", "coordinates": [ 1400408.908691004384309, 1156109.378080700756982 ] } },
{ "type": "Feature", "properties": { }, "geometry": { "type": "Point", "coordinates": [ 1401666.662120800931007, 1156125.542435732437298 ] } },
{ "type": "Feature", "properties": { }, "geometry": { "type": "Point", "coordinates": [ 1400436.185051707550883, 1156122.939830067101866 ] } },
{ "type": "Feature", "properties": { }, "geometry": { "type": "Point", "coordinates": [ 1402209.401199354091659, 1156159.08809179160744 ] } },
{ "type": "Feature", "properties": { }, "geometry": { "type": "Point", "coordinates": [ 1400836.357731365365908, 1156197.171051115263253 ] } },
{ "type": "Feature", "properties": { }, "geometry": { "type": "Point", "coordinates": [ 1398277.511584020452574, 1156168.964945741463453 ] } },
{ "type": "Feature", "properties": { }, "geometry": { "type": "Point", "coordinates": [ 1399617.616793863708153, 1156212.580803494667634 ] } },
{ "type": "Feature", "properties": { }, "geometry": { "type": "Point", "coordinates": [ 1398581.288101255893707, 1156232.128843867685646 ] } },
{ "type": "Feature", "properties": { }, "geometry": { "type": "Point", "coordinates": [ 1401159.297598640667275, 1156275.786959261400625 ] } },
{ "type": "Feature", "properties": { }, "geometry": { "type": "Point", "coordinates": [ 1400707.116507527651265, 1156275.747592554660514 ] } },
{ "type": "Feature", "properties": { }, "geometry": { "type": "Point", "coordinates": [ 1397321.125457550631836, 1156241.753892122302204 ] } },
{ "type": "Feature", "properties": { }, "geometry": { "type": "Point", "coordinates": [ 1396698.06632688594982, 1156238.374326349468902 ] } },
{ "type": "Feature", "properties": { }, "geometry": { "type": "Point", "coordinates": [ 1401778.886586734792218, 1156330.099244526820257 ] } },
{ "type": "Feature", "properties": { }, "geometry": { "type": "Point", "coordinates": [ 1400720.74457195866853, 1156339.459972680779174 ] } },
{ "type": "Feature", "properties": { }, "geometry": { "type": "Point", "coordinates": [ 1401541.857139754109085, 1156351.13435232732445 ] } },
{ "type": "Feature", "properties": { }, "geometry": { "type": "Point", "coordinates": [ 1401950.807672633556649, 1156364.565545554971322 ] } },
{ "type": "Feature", "properties": { }, "geometry": { "type": "Point", "coordinates": [ 1401892.839173415675759, 1156393.009377231355757 ] } },
{ "type": "Feature", "properties": { }, "geometry": { "type": "Point", "coordinates": [ 1399990.663741648662835, 1156401.679206083761528 ] } },
{ "type": "Feature", "properties": { }, "geometry": { "type": "Point", "coordinates": [ 1400385.313601144589484, 1156409.64569907868281 ] } },
{ "type": "Feature", "properties": { }, "geometry": { "type": "Point", "coordinates": [ 1396699.580773751949891, 1156367.481344725238159 ] } },
{ "type": "Feature", "properties": { }, "geometry": { "type": "Point", "coordinates": [ 1400416.510555281303823, 1156410.675790827954188 ] } },
{ "type": "Feature", "properties": { }, "geometry": { "type": "Point", "coordinates": [ 1399934.504094460746273, 1156410.946507113985717 ] } },
{ "type": "Feature", "properties": { }, "geometry": { "type": "Point", "coordinates": [ 1398894.645477655343711, 1156418.536976073635742 ] } },
{ "type": "Feature", "properties": { }, "geometry": { "type": "Point", "coordinates": [ 1396952.155866712564602, 1156400.251308236736804 ] } },
{ "type": "Feature", "properties": { }, "geometry": { "type": "Point", "coordinates": [ 1398587.171242891578004, 1156444.698859218740836 ] } },
{ "type": "Feature", "properties": { }, "geometry": { "type": "Point", "coordinates": [ 1398282.846379010239616, 1156450.376037365058437 ] } },
{ "type": "Feature", "properties": { }, "geometry": { "type": "Point", "coordinates": [ 1402208.817805893486366, 1156513.910869825398549 ] } },
{ "type": "Feature", "properties": { }, "geometry": { "type": "Point", "coordinates": [ 1401852.463580900803208, 1156534.200047775404528 ] } },
{ "type": "Feature", "properties": { }, "geometry": { "type": "Point", "coordinates": [ 1401022.629874169128016, 1156530.366714148782194 ] } },
{ "type": "Feature", "properties": { }, "geometry": { "type": "Point", "coordinates": [ 1399248.984225316438824, 1156515.397245085798204 ] } },
{ "type": "Feature", "properties": { }, "geometry": { "type": "Point", "coordinates": [ 1399623.324375774245709, 1156525.772084256866947 ] } },
{ "type": "Feature", "properties": { }, "geometry": { "type": "Point", "coordinates": [ 1401003.355445084394887, 1156563.239075012970716 ] } },
{ "type": "Feature", "properties": { }, "geometry": { "type": "Point", "coordinates": [ 1401218.320695756236091, 1156568.42345495079644 ] } },
{ "type": "Feature", "properties": { }, "geometry": { "type": "Point", "coordinates": [ 1401532.955742039950565, 1156574.783849190920591 ] } },
{ "type": "Feature", "properties": { }, "geometry": { "type": "Point", "coordinates": [ 1401774.371766105294228, 1156580.942320197122172 ] } },
{ "type": "Feature", "properties": { }, "geometry": { "type": "Point", "coordinates": [ 1401973.42165121785365, 1156616.39071239088662 ] } },
{ "type": "Feature", "properties": { }, "geometry": { "type": "Point", "coordinates": [ 1397326.294808736303821, 1156566.854743713978678 ] } },
{ "type": "Feature", "properties": { }, "geometry": { "type": "Point", "coordinates": [ 1400976.146632402203977, 1156613.229703826829791 ] } },
{ "type": "Feature", "properties": { }, "geometry": { "type": "Point", "coordinates": [ 1401394.504096432588995, 1156619.489938406040892 ] } },
{ "type": "Feature", "properties": { }, "geometry": { "type": "Point", "coordinates": [ 1399452.294075679965317, 1156625.039412423036993 ] } },
{ "type": "Feature", "properties": { }, "geometry": { "type": "Point", "coordinates": [ 1399255.011861100327224, 1156624.697645931039006 ] } },
{ "type": "Feature", "properties": { }, "geometry": { "type": "Point", "coordinates": [ 1400232.771692611277103, 1156640.206309874309227 ] } },
{ "type": "Feature", "properties": { }, "geometry": { "type": "Point", "coordinates": [ 1399940.573629556922242, 1156639.406617034692317 ] } },
{ "type": "Feature", "properties": { }, "geometry": { "type": "Point", "coordinates": [ 1400422.999475663295016, 1156674.888613529270515 ] } },
{ "type": "Feature", "properties": { }, "geometry": { "type": "Point", "coordinates": [ 1400562.960151268867776, 1156701.033862700220197 ] } }
]
}
